pyqcams/__init__.py
pyqcams/constants.py
pyqcams/numv.py
pyqcams/plotters.py
pyqcams/psave.py
pyqcams/pymar.py
pyqcams/util.py
PyQCAMS-1.0.3.dist-info/LICENSE
PyQCAMS-1.0.3.dist-info/METADATA
PyQCAMS-1.0.3.dist-info/WHEEL
PyQCAMS-1.0.3.dist-info/top_level.txt
PyQCAMS-1.0.3.dist-info/RECORD
