Metadata-Version: 2.1
Name: PyQCAMS
Version: 1.0.3
Summary: Python Quasi Classical Atom Molecule Scattering
Home-page: https://github.com/Rkoost/PyQCAMS
Author: Rian Koots
Author-email: rian.koots@stonybrook.edu
License: UNKNOWN
Platform: UNKNOWN
Requires-Dist: ipython (>=7.30)
Requires-Dist: matplotlib (>=3.7.1)
Requires-Dist: numpy (>=1.23.5)
Requires-Dist: pandas (>=1.2.4)
Requires-Dist: scipy (>=1.10.0)
Requires-Dist: multiprocess (>=0.70.14)
